om_pycycle-4.4.0.dist-info/licenses/LICENSE.txt
pycycle/__init__.py
pycycle/api.py
pycycle/connect_flow.py
pycycle/constants.py
pycycle/element_base.py
pycycle/flow_in.py
pycycle/mp_cycle.py
pycycle/passthrough.py
pycycle/viewers.py
pycycle/elements/US1976.py
pycycle/elements/__init__.py
pycycle/elements/ambient.py
pycycle/elements/bleed_out.py
pycycle/elements/cfd_start.py
pycycle/elements/combustor.py
pycycle/elements/compressor.py
pycycle/elements/compressor_map.py
pycycle/elements/cooling.py
pycycle/elements/duct.py
pycycle/elements/flight_conditions.py
pycycle/elements/flow_start.py
pycycle/elements/gearbox.py
pycycle/elements/inlet.py
pycycle/elements/mixer.py
pycycle/elements/nozzle.py
pycycle/elements/performance.py
pycycle/elements/shaft.py
pycycle/elements/splitter.py
pycycle/elements/turbine.py
pycycle/elements/turbine_map.py
pycycle/elements/test/__init__.py
pycycle/elements/test/test_ambient.py
pycycle/elements/test/test_bleed_out.py
pycycle/elements/test/test_cfd_start.py
pycycle/elements/test/test_combustor.py
pycycle/elements/test/test_compressor.py
pycycle/elements/test/test_compressor_map.py
pycycle/elements/test/test_compressor_od.py
pycycle/elements/test/test_cooling.py
pycycle/elements/test/test_duct.py
pycycle/elements/test/test_flightconditions.py
pycycle/elements/test/test_flow_start.py
pycycle/elements/test/test_inlet.py
pycycle/elements/test/test_mixer.py
pycycle/elements/test/test_nozzle.py
pycycle/elements/test/test_nozzle_CV_CD.py
pycycle/elements/test/test_shaft.py
pycycle/elements/test/test_splitter.py
pycycle/elements/test/test_turbine.py
pycycle/elements/test/test_turbine_map.py
pycycle/elements/test/test_turbine_od.py
pycycle/elements/test/test_usatm1976.py
pycycle/elements/test/reg_data/ambient.csv
pycycle/elements/test/reg_data/combustorJP7.csv
pycycle/elements/test/reg_data/compressor.csv
pycycle/elements/test/reg_data/compressorOD1.csv
pycycle/elements/test/reg_data/duct.csv
pycycle/elements/test/reg_data/flowstart.csv
pycycle/elements/test/reg_data/inlet.csv
om_pycycle-4.4.0.dist-info/METADATA
om_pycycle-4.4.0.dist-info/WHEEL
om_pycycle-4.4.0.dist-info/top_level.txt
om_pycycle-4.4.0.dist-info/RECORD
